topsis_bin/__init__.py
topsis_bin/topsis.py
topsis_khushnoor_102303219-1.1.1.dist-info/METADATA
topsis_khushnoor_102303219-1.1.1.dist-info/WHEEL
topsis_khushnoor_102303219-1.1.1.dist-info/entry_points.txt
topsis_khushnoor_102303219-1.1.1.dist-info/top_level.txt
topsis_khushnoor_102303219-1.1.1.dist-info/RECORD
