Metadata-Version: 2.4
Name: Topsis-Khushnoor-102303219
Version: 1.1.1
Summary: A Python package for TOPSIS MCDM problems
Home-page: https://github.com/KKaur170/Topsis-Khushnoor-102303219
Author: Khushnoor Kaur
Author-email: kkaur1_be23@thapar.edu
Classifier: Programming Language :: Python :: 3
Classifier: License :: OSI Approved :: MIT License
Classifier: Operating System :: OS Independent
Requires-Dist: pandas
Requires-Dist: numpy
Dynamic: author
Dynamic: author-email
Dynamic: classifier
Dynamic: description
Dynamic: description-content-type
Dynamic: home-page
Dynamic: requires-dist
Dynamic: summary
